CHANGES.txt
LICENSE.txt
README.txt
setup.cfg
setup.py
version.txt
raisin/__init__.py
raisin.resource.egg-info/PKG-INFO
raisin.resource.egg-info/SOURCES.txt
raisin.resource.egg-info/dependency_links.txt
raisin.resource.egg-info/entry_points.txt
raisin.resource.egg-info/namespace_packages.txt
raisin.resource.egg-info/not-zip-safe
raisin.resource.egg-info/requires.txt
raisin.resource.egg-info/top_level.txt
raisin/resource/__init__.py
raisin/resource/discovery.py
raisin/resource/experiment.py
raisin/resource/expression.py
raisin/resource/mapping.py
raisin/resource/project.py
raisin/resource/read.py
raisin/resource/replicate.py
raisin/resource/root.py
raisin/resource/splicing.py
raisin/resource/utils.py
raisin/resource/tests/test_resource.py